[
  {
    "title": "司政边巴次仁继续展开拉达克访问行程",
    "date": "2026-07-08",
    "source": "tibet.com",
    "source_name": "藏人行政中央官网",
    "body": "7月8日司政边巴次仁在拉达克第三天访问，走访索南林藏人定居点四营地、图伯特儿童村及老人院。视察基础设施，鼓励学生学藏语，慰问流亡藏人。此次访问是连任后首次大规模出访，凸显对边境藏人社区重视。拉达克地处中印边境战略要地。"
  },
  {
    "title": "司政边巴次仁抵达拉达克展开正式访问",
    "date": "2026-07-06",
    "source": "tibet.com",
    "source_name": "藏人行政中央官网",
    "body": "7月6日司政抵达拉达克展开正式访问，连任后首次。视察索南林定居点首批营地，与社区领袖讨论发展、就业、教育议题。"
  },
  {
    "title": "第十八届图伯特人民议会持续运作",
    "date": "2026-07-07",
    "source": "tibet.com",
    "source_name": "藏人行政中央官网",
    "body": "议会自6月1日成立以来持续运作。议长卓玛次仁部署国际游说和社区建设，副议长堪布索朗丹培强调文化传承。议员深入选区调研。"
  }
]